{
  "title": "Inflácia sa neporazila, len skrývala. Ako geopolitický šok vrátil európsku ekonomiku do reality",
  "slug": "inflacia-sa-neporazila-len-skryvala-ako-geopoliticky-sok-vra",
  "date": "2026-03-31",
  "tags": [
    "inflácia",
    "ekonomika",
    "geopolitika",
    "energetická bezpečnosť",
    "USA",
    "Európa"
  ],
  "source_url": "https://www.youtube.com/watch?v=njdxQsZsJBQ",
  "content": "<h2>Ilúzia vitazstva, ktorá trvala 66 dní</h2>\n\n<p>Január 2025 bol mesiacom falošného optimizmu. Zatiaľ čo americká administratíva oslavovala <strong>porážku inflácie</strong> a globálne trhy si oddychli, ekonomická realita sa chystala na tvrdú reštart. Ako to často bývá v politike a ekonómii: najväčšie problémy sa nikdy neriešia, iba sa nechávajú na chvíľu odpočívať.</p>\n\n<p>Podľa analýzy video kanála <em>House of El</em> sa za sedem týždňov uskutočnil v USA presný opak toho, čo kľúčoví rozhodovací činitelia vyhlasovali. Inflácia – ktorú po januárových číslach OECD všetci považovali za kontrolovanú – sa vrátila s väčšou silou, čím sa Spojené štáty dostali do pozície <strong>krajiny s najhorším inflačným tlakom v skupine G7</strong>. Nie je to len české číslo v tabuľke. Je to dôkaz toho, ako krehké sú nástroje, ktorými sa pokúšame kontrolovať modernu ekonomiku.</p>\n\n<h2>Čo sa stalo v medzitime? Geopolitika vs. ekonomika</h2>\n\n<p>Čriepky začali padať hneď v februári. Eskalácia napätia pri Hormúzskom prielive – jednom z kritických bodov globálneho obchodu – odstránila značnú časť svetového zásobovania ropou z dostupných trhov. Nie fyzicky. Psychologicky a trhom postačuje aj <em>hrozba</em> narušenia dodávok.</p>\n\n<p>Výsledok bol brutálny a predvídateľný:</p>\n\n<ul>\n<li><strong>Cena ropy skočila nad 100 dolárov za barel</strong> – úroveň, ktorú svet nezažil od čias, keď sa všetci báli recesie</li>\n<li>Transport sa stalo drahší, čo sa automaticky pretavilo do cien potravín a priemyselného tovaru</li>\n<li>Inflácia sa vrátila, nie ako návrhly problém, ale ako hlboké vryté korene cez celú ekonomickú štruktúru</li>\n</ul>\n\n<h2>Prečo je to dôležité pre Slovensko a Európu?</h2>\n\n<p>Slovenský čitateľ by sa tu mohol opýtať: <em>A čo nás sa to má týkať?</em> Odpoveď je prostá a nepríjemná.</p>\n\n<p>Európa – a najmä Slovensko – je energeticky zraniteľnejší ako USA. Zatiaľ čo americká ekonomika si môže dovoliť energetických výkyvy, my sme na importoch závislí. Keď rastie cena energie na svetovom trhu, prvých pocíťujú to remeselníci, rodiny a malí podnikatelia u nás.</p>\n\n<p><strong>Druhý problém je politický.</strong> Táto eskalácia pri Hormúze nie je len ekonomickou uviazačkou. Je to signál, že geopolitické riziko sa vracia ako primárny faktor výraznosti trhov. Európska politika sa musí pripraviť na obdobie, keď stabilita dodávok energií nebude samozrejmosťou, ale objektom strategického záujmu väčších mocností.</p>\n\n<h2>Lekcia, ktorú nechceme prijať</h2>\n\n<p>Prečo je táto analýza dôležitá? Pretože poukazuje na fundamentálny problém súčasného ekonomického rámca: <strong>inflácia sa nikdy neporazí, iba sa odsúva</strong>. Kým sa nezmenšia strukturálne problémy – energetická závislosť, globálne dodávateľské reťazce, geopolitické napätia – budeme sa točiť v kruhu.</p>\n\n<p>Trump slávil porážku inflácie. O 66 dní neskôr museli uznať, že všetko sa vrátilo. To nie je jeho chyba výlučne – globálne ekonomické sily sú väčšie ako ktorýkoľvek politik – ale je to dôkaz, že bez hlbších zmien sa problémy len berú a potom vracia.</p>\n\n<p>Pre Slovensko to znamená jediné: <strong>budovať rezilienciu teraz, kým sme si to ešte môžu dovoliť.</strong></p>",
  "generated_at": "2026-03-31T20:06:31.408114+00:00",
  "source_video_title": "Trump's 'Victory' BACKFIRED - Declared Inflation Defeated, Now WORST in G7, 66 Days Later"
}